uptobox/Client.py
uptobox/Constants.py
uptobox/Core.py
uptobox/Error.py
uptobox/Gateway.py
uptobox/Types.py
uptobox/__init__.py
uptobox-1.1.0.dist-info/LICENSE
uptobox-1.1.0.dist-info/METADATA
uptobox-1.1.0.dist-info/WHEEL
uptobox-1.1.0.dist-info/top_level.txt
uptobox-1.1.0.dist-info/RECORD
