Metadata-Version: 2.1
Name: uptobox
Version: 1.1.0
Summary: A simple API wrapper for Uptobox.
Home-page: https://github.com/ArticOff/uptobox
Author: Artic#3065
Author-email: artic.admisoffi@gmail.com
Maintainer: Artic#3065
Maintainer-email: artic.admisoffi@gmail.com
License: MIT
Platform: UNKNOWN
Classifier: Development Status :: 5 - Production/Stable
Classifier: License :: OSI Approved :: MIT License
Classifier: Intended Audience :: Developers
Classifier: Intended Audience :: Customer Service
Classifier: Natural Language :: English
Classifier: Programming Language :: Python :: 3
Classifier: Programming Language :: Python
Classifier: Environment :: Console
Classifier: Environment :: Win32 (MS Windows)
Classifier: Framework :: AsyncIO
Classifier: Framework :: Pytest
Classifier: Operating System :: OS Independent
Classifier: Topic :: Internet
License-File: LICENSE
Requires-Dist: aiohttp
